trueface/__init__.py
trueface/api.py
trueface/detector.py
trueface/enroll.py
trueface/helper.py
trueface/logo.png
trueface/mtcnn_detector.py
trueface/server.py
trueface/test.py
trueface/trueface.py
trueface/utilities.py
trueface/video.py
trueface/model/det1-0001.params
trueface/model/det1-symbol.json
trueface/model/det1.caffemodel
trueface/model/det1.prototxt
trueface/model/det2-0001.params
trueface/model/det2-symbol.json
trueface/model/det2.caffemodel
trueface/model/det2.prototxt
trueface/model/det3-0001.params
trueface/model/det3-symbol.json
trueface/model/det3.caffemodel
trueface/model/det3.prototxt
trueface/model/det4-0001.params
trueface/model/det4-symbol.json
trueface/model/det4.caffemodel
trueface/model/det4.prototxt
trueface_server/__init__.py
trueface_server/api.py
trueface_server/detector.py
trueface_server/helper.py
trueface_server/mtcnn_detector.py
trueface_server/server.py
trueface_server/test.py
trueface_server/utilities.py
trueface_server/video.py
trueface_server/model/det1-0001.params
trueface_server/model/det1-symbol.json
trueface_server/model/det1.caffemodel
trueface_server/model/det1.prototxt
trueface_server/model/det2-0001.params
trueface_server/model/det2-symbol.json
trueface_server/model/det2.caffemodel
trueface_server/model/det2.prototxt
trueface_server/model/det3-0001.params
trueface_server/model/det3-symbol.json
trueface_server/model/det3.caffemodel
trueface_server/model/det3.prototxt
trueface_server/model/det4-0001.params
trueface_server/model/det4-symbol.json
trueface_server/model/det4.caffemodel
trueface_server/model/det4.prototxt
trueface_server-0.36.dist-info/METADATA
trueface_server-0.36.dist-info/RECORD
trueface_server-0.36.dist-info/WHEEL
trueface_server-0.36.dist-info/entry_points.txt
trueface_server-0.36.dist-info/top_level.txt
